topfarm/__init__.py
topfarm/_topfarm.py
topfarm/_version.py
topfarm/deprecated_mongo_recorder.py
topfarm/deprecated_topfarm_problems.py
topfarm/easy_drivers.py
topfarm/parallel_runner.py
topfarm/plotting.py
topfarm/recorders.py
topfarm/utils.py
topfarm/wind_farm_cluster.py
topfarm/workshop.py
topfarm/constraint_components/__init__.py
topfarm/constraint_components/_constraint.py
topfarm/constraint_components/boundary.py
topfarm/constraint_components/capacity.py
topfarm/constraint_components/constrained_generator.py
topfarm/constraint_components/constraint_aggregation.py
topfarm/constraint_components/deprecated_boundary_component.py
topfarm/constraint_components/load.py
topfarm/constraint_components/penalty_component.py
topfarm/constraint_components/spacing.py
topfarm/cost_models/__init__.py
topfarm/cost_models/cost_model_wrappers.py
topfarm/cost_models/dummy.py
topfarm/cost_models/py_wake_wrapper.py
topfarm/cost_models/topfarm_components.py
topfarm/cost_models/economic_models/__init__.py
topfarm/cost_models/economic_models/finance_wrapper.py
topfarm/cost_models/electrical/__init__.py
topfarm/cost_models/electrical/optiwindnet_wrapper.py
topfarm/cost_models/electrical/simple_msp.py
topfarm/cost_models/fuga/__init__.py
topfarm/cost_models/fuga/py_fuga.py
topfarm/cost_models/utils/__init__.py
topfarm/cost_models/utils/spanning_tree.py
topfarm/drivers/__init__.py
topfarm/drivers/genetic_algorithm_driver.py
topfarm/drivers/random_search_driver.py
topfarm/drivers/stochastic_gradient_descent_driver.py
topfarm/examples/__init__.py
topfarm/examples/bathymetry_ficticio.py
topfarm/examples/energy_island.py
topfarm/examples/input_ts.csv
topfarm/examples/data/__init__.py
topfarm/examples/data/parque_ficticio_offshore.py
topfarm/examples/deprecated/MongoDB_recorder.ipynb
topfarm/examples/deprecated/README.md
topfarm/examples/deprecated/cables.ipynb
topfarm/examples/deprecated/cost_models.ipynb
topfarm/examples/deprecated/roads_and_cables.ipynb
topfarm-2.6.1.dist-info/METADATA
topfarm-2.6.1.dist-info/WHEEL
topfarm-2.6.1.dist-info/licenses/LICENSE
topfarm-2.6.1.dist-info/RECORD
